presence/__init__.py
presence/client.py
presence/main.py
presence/parser.py
presence/server.py
presence/sock.py
presence/types.py
python_presence-0.1.6.data/data/share/python-presence/presence.service
python_presence-0.1.6.data/data/share/python-presence/python-presence.service
python_presence-0.1.6.data/scripts/python-presence
python_presence-0.1.6.dist-info/LICENSE
python_presence-0.1.6.dist-info/METADATA
python_presence-0.1.6.dist-info/WHEEL
python_presence-0.1.6.dist-info/top_level.txt
python_presence-0.1.6.dist-info/RECORD
