Metadata-Version: 2.1
Name: python-presence
Version: 0.1.6
Summary: minimal implementation of a serverless XMPP client
Home-page: https://github.com/jmechnich/python-presence
Author: Joerg Mechnich
Author-email: joerg.mechnich@gmail.com
License: GNU GPLv3
Classifier: Programming Language :: Python :: 3
Classifier: License :: OSI Approved :: GNU General Public License v3 (GPLv3)
Classifier: Operating System :: POSIX :: Linux
Requires-Python: >=3.6
License-File: LICENSE
Requires-Dist: pidfile
Requires-Dist: psutil
Requires-Dist: python-daemon
